<?xml version="1.0" encoding="UTF-8"?>
<!DOCTYPE plist PUBLIC "-//Apple//DTD PLIST 1.0//EN" "http://www.apple.com/DTDs/PropertyList-1.0.dtd"/>

<plist version="1.0">
    <dict>
        <key>ROOT</key>
        <array>
            <dict>
                <key>id</key>
                <string>144</string>
                <key>Image</key>
                <dict>
                    <key>value</key>
                    <string>139</string>
                </dict>
            </dict>
            <dict>
                <key>id</key>
                <string>167</string>
                <key>Image</key>
                <dict>
                    <key>value</key>
                    <string>153</string>
                </dict>
            </dict>
            <dict>
                <key>id</key>
                <string>303</string>
                <key>Image</key>
                <dict>
                    <key>value</key>
                    <string>279</string>
                </dict>
            </dict>
            <dict>
                <key>id</key>
                <string>858</string>
                <key>Image</key>
                <dict>
                    <key>value</key>
                    <string>853</string>
                </dict>
            </dict>
            <dict>
                <key>id</key>
                <string>880</string>
                <key>Image</key>
                <dict>
                    <key>value</key>
                    <string>872</string>
                </dict>
            </dict>
            <dict>
                <key>id</key>
                <string>1085</string>
                <key>Image</key>
                <dict>
                    <key>value</key>
                    <string>1081</string>
                </dict>
            </dict>
            <dict>
                <key>id</key>
                <string>1231</string>
                <key>Image</key>
                <dict>
                    <key>value</key>
                    <string>1209</string>
                </dict>
            </dict>
            <dict>
                <key>id</key>
                <string>1309</string>
                <key>Image</key>
                <dict>
                    <key>value</key>
                    <string>1305</string>
                </dict>
            </dict>
            <dict>
                <key>id</key>
                <string>1591</string>
                <key>Image</key>
                <dict>
                    <key>value</key>
                    <string>1569</string>
                </dict>
            </dict>
            <dict>
                <key>id</key>
                <string>1639</string>
                <key>Image</key>
                <dict>
                    <key>value</key>
                    <string>1634</string>
                </dict>
            </dict>
            <dict>
                <key>id</key>
                <string>1929</string>
                <key>Image</key>
                <dict>
                    <key>value</key>
                    <string>1923</string>
                </dict>
            </dict>
            <dict>
                <key>id</key>
                <string>2107</string>
                <key>Image</key>
                <dict>
                    <key>value</key>
                    <string>2102</string>
                </dict>
            </dict>
            <dict>
                <key>id</key>
                <string>2145</string>
                <key>Image</key>
                <dict>
                    <key>value</key>
                    <string>2140</string>
                </dict>
            </dict>
            <dict>
                <key>id</key>
                <string>2156</string>
                <key>Image</key>
                <dict>
                    <key>value</key>
                    <string>2151</string>
                </dict>
            </dict>
            <dict>
                <key>id</key>
                <string>2167</string>
                <key>Image</key>
                <dict>
                    <key>value</key>
                    <string>2162</string>
                </dict>
            </dict>
            <dict>
                <key>id</key>
                <string>2218</string>
                <key>Image</key>
                <dict>
                    <key>value</key>
                    <string>2213</string>
                </dict>
            </dict>
            <dict>
                <key>id</key>
                <string>2267</string>
                <key>Image</key>
                <dict>
                    <key>value</key>
                    <string>2262</string>
                </dict>
            </dict>
            <dict>
                <key>id</key>
                <string>2278</string>
                <key>Image</key>
                <dict>
                    <key>value</key>
                    <string>2273</string>
                </dict>
            </dict>
            <dict>
                <key>id</key>
                <string>2289</string>
                <key>Image</key>
                <dict>
                    <key>value</key>
                    <string>2284</string>
                </dict>
            </dict>
            <dict>
                <key>id</key>
                <string>2873</string>
                <key>Image</key>
                <dict>
                    <key>value</key>
                    <string>2868</string>
                </dict>
            </dict>
            <dict>
                <key>id</key>
                <string>2884</string>
                <key>Image</key>
                <dict>
                    <key>value</key>
                    <string>2879</string>
                </dict>
            </dict>
            <dict>
                <key>id</key>
                <string>3004</string>
                <key>Image</key>
                <dict>
                    <key>value</key>
                    <string>2999</string>
                </dict>
            </dict>
            <dict>
                <key>id</key>
                <string>3361</string>
                <key>Image</key>
                <dict>
                    <key>value</key>
                    <string>3352</string>
                </dict>
            </dict>
            <dict>
                <key>id</key>
                <string>4375</string>
                <key>Image</key>
                <dict>
                    <key>value</key>
                    <string>4370</string>
                </dict>
            </dict>
            <dict>
                <key>id</key>
                <string>6157</string>
                <key>Image</key>
                <dict>
                    <key>value</key>
                    <string>6152</string>
                </dict>
            </dict>
            <dict>
                <key>id</key>
                <string>6462</string>
                <key>Image</key>
                <dict>
                    <key>value</key>
                    <string>6457</string>
                </dict>
            </dict>
            <dict>
                <key>id</key>
                <string>6475</string>
                <key>Image</key>
                <dict>
                    <key>value</key>
                    <string>6468</string>
                </dict>
            </dict>
        </array>
    </dict>
</plist>
